LICENSE
MANIFEST.in
README.md
setup.py
examples/example1.py
examples/example2.py
examples/example3.py
examples/example4.py
examples/dataset/6.lst
examples/dataset/mat.g7
graph7/__init__.py
graph7/graph7.py
graph7/wrapper.c
graph7/graph7/src/graph7.c
graph7/graph7/src/graph7.h
pygraph7.egg-info/PKG-INFO
pygraph7.egg-info/SOURCES.txt
pygraph7.egg-info/dependency_links.txt
pygraph7.egg-info/top_level.txt
tests/fuzzy_tests.py